NetTect_STT/__init__.py
nettect_stt-0.1.dist-info/METADATA
nettect_stt-0.1.dist-info/WHEEL
nettect_stt-0.1.dist-info/top_level.txt
nettect_stt-0.1.dist-info/RECORD
