Metadata-Version: 2.1
Name: nettect-stt
Version: 0.1
Summary: This is Speech to Text Recognition tool create by Naeem Ali
Author: Naeem Ali
Author-email: example@gmail.com
